shopee_captcha_solver/__init__.py
shopee_captcha_solver/api.py
shopee_captcha_solver/async_playwright_util.py
shopee_captcha_solver/asyncplaywrightsolver.py
shopee_captcha_solver/asyncsolver.py
shopee_captcha_solver/captchatype.py
shopee_captcha_solver/downloader.py
shopee_captcha_solver/geometry.py
shopee_captcha_solver/models.py
shopee_captcha_solver/playwright_util.py
shopee_captcha_solver/playwrightsolver.py
shopee_captcha_solver/selectors.py
shopee_captcha_solver/selenium_util.py
shopee_captcha_solver/seleniumsolver.py
shopee_captcha_solver/syncsolver.py
shopee_captcha_solver/tests/__init__.py
shopee_captcha_solver/tests/test_api.py
shopee_captcha_solver/tests/test_asyncplaywrightsolver.py
shopee_captcha_solver/tests/test_downloader.py
shopee_captcha_solver/tests/test_playwrightsolver.py
shopee_captcha_solver/tests/test_seleniumsolver.py
shopee_captcha_solver-0.1.2.dist-info/METADATA
shopee_captcha_solver-0.1.2.dist-info/WHEEL
shopee_captcha_solver-0.1.2.dist-info/top_level.txt
shopee_captcha_solver-0.1.2.dist-info/RECORD
