Metadata-Version: 2.1
Name: shopee-captcha-solver
Version: 0.1.2
Summary: This package integrates with Selenium or Playwright to solve any Shopee captcha in one line of code.
Author-email: Toughdata LLC <greg@toughdata.net>
Project-URL: Homepage, https://www.sadcaptcha.com
Project-URL: Source, https://github.com/gbiz123/shopee-captcha-solver/
Keywords: shopee,captcha,solver,selenium,playwright
Classifier: Intended Audience :: Developers
Classifier: Topic :: Software Development :: Build Tools
Classifier: Programming Language :: Python :: 3.10
Classifier: Programming Language :: Python :: 3.11
Classifier: Programming Language :: Python :: 3.12
Classifier: Programming Language :: Python :: 3 :: Only
Requires-Python: >=3.10
Requires-Dist: selenium
Requires-Dist: webdriver-manager
Requires-Dist: pydantic
Requires-Dist: requests
Requires-Dist: pytest
Requires-Dist: pytest-asyncio
Requires-Dist: playwright
Requires-Dist: playwright-stealth
Requires-Dist: undetected_chromedriver
Requires-Dist: setuptools
